teledown/__init__.py
teledown/__main__.py
teledown-0.1.2.dist-info/METADATA
teledown-0.1.2.dist-info/WHEEL
teledown-0.1.2.dist-info/entry_points.txt
teledown-0.1.2.dist-info/top_level.txt
teledown-0.1.2.dist-info/RECORD
