Metadata-Version: 2.1
Name: teledown
Version: 0.1.2
Summary: A simple CLI tool to download videos from Telegram channels
Home-page: https://github.com/konyilwin/teledown
Author: Nyi Nyi Lwin
Author-email: hello.nyinyilwin@gmail.com
Classifier: Programming Language :: Python :: 3
Classifier: License :: OSI Approved :: MIT License
Classifier: Operating System :: OS Independent
Requires-Python: >=3.6
Requires-Dist: click
Requires-Dist: telethon
Requires-Dist: tabulate
Requires-Dist: tqdm
